LICENSE.txt
MANIFEST.in
README.md
setup.py
python_vipaccess2.egg-info/PKG-INFO
python_vipaccess2.egg-info/SOURCES.txt
python_vipaccess2.egg-info/dependency_links.txt
python_vipaccess2.egg-info/entry_points.txt
python_vipaccess2.egg-info/requires.txt
python_vipaccess2.egg-info/top_level.txt
tests/test_utils.py
vipaccess2/__init__.py
vipaccess2/cli.py
vipaccess2/patharg.py
vipaccess2/provision.py