Metadata-Version: 1.1
Name: python-vipaccess2
Version: 0.3.6
Summary: A free software implementation of Symantec's VIP Access application and protocol, a fork of a fork.
Home-page: https://github.com/chris17453/python-vipaccess
Author: Forest Crossman
Author-email: cyrozap@gmail.com
License: Apache 2.0
Keywords: development
Platform: UNKNOWN
Classifier: Development Status :: 3 - Alpha
Classifier: Intended Audience :: Developers
Classifier: Topic :: Software Development :: Libraries :: Python Modules
Classifier: Topic :: Utilities
Classifier: License :: OSI Approved :: Apache Software License
Classifier: Programming Language :: Python :: 2
Classifier: Programming Language :: Python :: 2.7
Classifier: Programming Language :: Python :: 3
Classifier: Programming Language :: Python :: 3.3
Classifier: Programming Language :: Python :: 3.4
Classifier: Programming Language :: Python :: 3.5
